pytorch_warmup/__init__.py
pytorch_warmup/base.py
pytorch_warmup/radam.py
pytorch_warmup/untuned.py
pytorch_warmup-0.1.1.dist-info/LICENSE
pytorch_warmup-0.1.1.dist-info/METADATA
pytorch_warmup-0.1.1.dist-info/WHEEL
pytorch_warmup-0.1.1.dist-info/top_level.txt
pytorch_warmup-0.1.1.dist-info/RECORD
