Metadata-Version: 2.1
Name: pytorch-warmup
Version: 0.1.1
Summary: A PyTorch Extension for Learning Rate Warmup
Home-page: https://github.com/Tony-Y/pytorch_warmup
Author: Takenori Yamamoto
Author-email: yamamoto.takenory@gmail.com
Classifier: Intended Audience :: Science/Research
Classifier: Topic :: Scientific/Engineering :: Artificial Intelligence
Classifier: Topic :: Software Development :: Libraries :: Python Modules
Classifier: Programming Language :: Python :: 3.7
Classifier: Programming Language :: Python :: 3.8
Classifier: Operating System :: OS Independent
Classifier: License :: OSI Approved :: MIT License
Requires-Python: >=3.7
License-File: LICENSE
Requires-Dist: torch (>=1.1)
